kedro_great/__init__.py
kedro_great/command.py
kedro_great/data.py
kedro_great/exceptions.py
kedro_great/kedro_great.py
kedro_great/cli/__init__.py
kedro_great/cli/cli.py
kedro_great/cli/datasource.py
kedro_great/cli/init.py
kedro_great/cli/suite.py
kedro_great/hook/__init__.py
kedro_great/hook/kedro_great.py
kedro_great-0.2.7.dist-info/LICENSE
kedro_great-0.2.7.dist-info/METADATA
kedro_great-0.2.7.dist-info/WHEEL
kedro_great-0.2.7.dist-info/entry_points.txt
kedro_great-0.2.7.dist-info/top_level.txt
kedro_great-0.2.7.dist-info/RECORD
