Metadata-Version: 2.1
Name: kedro-great
Version: 0.2.7
Summary: Kedro Great makes integrating Great Expectations with Kedro easy!
Home-page: https://github.com/tamsanh/kedro-great.git
Author: Tam-Sanh Nguyen
Author-email: tamsanh@gmail.com
License: MIT
Platform: UNKNOWN
Classifier: License :: OSI Approved :: MIT License
Classifier: Programming Language :: Python :: 3.6
Classifier: Programming Language :: Python :: 3.7
Requires-Dist: kedro (>=0.16.0)
Requires-Dist: kedro[pandas] (>=0.16.0)
Requires-Dist: kedro[spark] (>=0.16.0)
Requires-Dist: great-expectations
Requires-Dist: pyspark
Requires-Dist: pandas
